emagpy/Problem.py
emagpy/Survey.py
emagpy/__init__.py
emagpy/hankelpts.txt
emagpy/hankelwts0.txt
emagpy/hankelwts1.txt
emagpy/invertHelper.py
emagpy/j0_120.txt
emagpy/j1_140.txt
emagpy/pcs.csv
emagpy-1.4.1.dist-info/LICENSE
emagpy-1.4.1.dist-info/METADATA
emagpy-1.4.1.dist-info/WHEEL
emagpy-1.4.1.dist-info/top_level.txt
emagpy-1.4.1.dist-info/RECORD
