Metadata-Version: 2.1
Name: emagpy
Version: 1.4.1
Summary: API for FDEM inversion and data manipulation
Home-page: https://gitlab.com/hkex/emagpy
Author: HKEx
Classifier: Programming Language :: Python :: 3
Classifier: License :: OSI Approved :: GNU General Public License v3 (GPLv3)
Classifier: Operating System :: OS Independent
License-File: LICENSE
Requires-Dist: numpy
Requires-Dist: matplotlib
Requires-Dist: pandas
Requires-Dist: scipy
Requires-Dist: pyproj
Requires-Dist: spotpy
Requires-Dist: joblib
Requires-Dist: tqdm
Requires-Dist: rasterio
